jgd/__init__.py
jgd/jgd.py
jigot-2.0.1.dist-info/LICENSE
jigot-2.0.1.dist-info/METADATA
jigot-2.0.1.dist-info/WHEEL
jigot-2.0.1.dist-info/entry_points.txt
jigot-2.0.1.dist-info/top_level.txt
jigot-2.0.1.dist-info/RECORD
