Metadata-Version: 2.1
Name: jigot
Version: 2.0.1
Summary: easy to make / discord bot with template
Home-page: https://discord.gg/UKYKatXGVJ
Author: JiGOT-Dev
Author-email: meoawlove.bam@gmail.com
Project-URL: Bug Tracker, https://github.com/JiGOT-Dev/jigot/issues
Classifier: Programming Language :: Python :: 3
Classifier: License :: OSI Approved :: MIT License
Requires-Python: >=3.6
License-File: LICENSE
